endex_factset_global_prices/__init__.py
endex_factset_global_prices/_base_client.py
endex_factset_global_prices/_client.py
endex_factset_global_prices/_compat.py
endex_factset_global_prices/_constants.py
endex_factset_global_prices/_exceptions.py
endex_factset_global_prices/_files.py
endex_factset_global_prices/_models.py
endex_factset_global_prices/_qs.py
endex_factset_global_prices/_resource.py
endex_factset_global_prices/_response.py
endex_factset_global_prices/_streaming.py
endex_factset_global_prices/_types.py
endex_factset_global_prices/_version.py
endex_factset_global_prices/py.typed
endex_factset_global_prices/_utils/__init__.py
endex_factset_global_prices/_utils/_logs.py
endex_factset_global_prices/_utils/_proxy.py
endex_factset_global_prices/_utils/_reflection.py
endex_factset_global_prices/_utils/_streams.py
endex_factset_global_prices/_utils/_sync.py
endex_factset_global_prices/_utils/_transform.py
endex_factset_global_prices/_utils/_typing.py
endex_factset_global_prices/_utils/_utils.py
endex_factset_global_prices/lib/.keep
endex_factset_global_prices/resources/__init__.py
endex_factset_global_prices/resources/annualized_dividends.py
endex_factset_global_prices/resources/corporate_actions.py
endex_factset_global_prices/resources/prices.py
endex_factset_global_prices/resources/returns.py
endex_factset_global_prices/resources/security_shares.py
endex_factset_global_prices/resources/batch_processings/__init__.py
endex_factset_global_prices/resources/batch_processings/batch_processings.py
endex_factset_global_prices/resources/batch_processings/batch_results.py
endex_factset_global_prices/resources/batch_processings/batch_status.py
endex_factset_global_prices/types/__init__.py
endex_factset_global_prices/types/annualized_dividend_create_params.py
endex_factset_global_prices/types/annualized_dividend_list_params.py
endex_factset_global_prices/types/annualized_dividend_response.py
endex_factset_global_prices/types/corporate_action_create_params.py
endex_factset_global_prices-0.1.0a1.dist-info/METADATA
endex_factset_global_prices-0.1.0a1.dist-info/WHEEL
endex_factset_global_prices-0.1.0a1.dist-info/licenses/LICENSE
endex_factset_global_prices-0.1.0a1.dist-info/RECORD
